mlserver_tempo/__init__.py
mlserver_tempo/tempo.py
mlserver_tempo/version.py
mlserver_tempo-0.3.1.dev5.dist-info/LICENSE
mlserver_tempo-0.3.1.dev5.dist-info/METADATA
mlserver_tempo-0.3.1.dev5.dist-info/WHEEL
mlserver_tempo-0.3.1.dev5.dist-info/top_level.txt
mlserver_tempo-0.3.1.dev5.dist-info/RECORD
