Metadata-Version: 2.1
Name: mlserver-tempo
Version: 0.3.1.dev5
Summary: MLOps runtime for MLServer
Home-page: https://github.com/SeldonIO/MLServer.git
Author: Seldon Technologies Ltd.
Author-email: hello@seldon.io
License: Apache 2.0
Platform: UNKNOWN
Requires-Dist: mlserver
Requires-Dist: mlops-tempo
